<?xml version="1.0" encoding="UTF-8"?>
<Language_Data>
  <string>
    <Key>TEXT_01</Key>
    <Content>Σύστημα</Content>
  </string>
  <string>
    <Key>TEXT_02</Key>
    <Content>Πίσω στο παιχνίδι</Content>
  </string>
  <string>
    <Key>TEXT_03</Key>
    <Content>Κλείστε το πρόγραμμα επεξεργασίας χάρτη</Content>
  </string>
  <string>
    <Key>TEXT_04</Key>
    <Content>Ανοίξτε το πρόγραμμα επεξεργασίας χάρτη</Content>
  </string>
  <string>
    <Key>TEXT_05</Key>
    <Content>Κλείστε το πρόγραμμα επεξεργασίας ήχου</Content>
  </string>
  <string>
    <Key>TEXT_06</Key>
    <Content>Ανοίξτε το πρόγραμμα επεξεργασίας ήχου</Content>
  </string>
  <string>
    <Key>TEXT_07</Key>
    <Content>  Επιλογές Γλώσσας :</Content>
  </string>
  <string>
    <Key>TEXT_08</Key>
    <Content>Εγκαταλείπω</Content>
  </string>
  <string>
    <Key>TEXT_09</Key>
    <Content>Ρύθμιση ήχου κολοκύθες</Content>
  </string>
  <string>
    <Key>TEXT_10</Key>
    <Content>* Αρχεία ήχου</Content>
  </string>
  <string>
    <Key>TEXT_11</Key>
    <Content>  Ονομα αρχείου</Content>
  </string>
  <string>
    <Key>TEXT_12</Key>
    <Content>  Τύπος</Content>
  </string>
  <string>
    <Key>TEXT_13</Key>
    <Content>  Μορφή</Content>
  </string>
  <string>
    <Key>TEXT_14</Key>
    <Content>  Κανάλια</Content>
  </string>
  <string>
    <Key>TEXT_15</Key>
    <Content>  Bits</Content>
  </string>
  <string>
    <Key>TEXT_16</Key>
    <Content>  Βρόχος</Content>
  </string>
  <string>
    <Key>TEXT_17</Key>
    <Content>  ChannelGroup</Content>
  </string>
  <string>
    <Key>TEXT_18</Key>
    <Content>  κατάσταση</Content>
  </string>
  <string>
    <Key>TEXT_19</Key>
    <Content>Ναί</Content>
  </string>
  <string>
    <Key>TEXT_20</Key>
    <Content>Οχι</Content>
  </string>
  <string>
    <Key>TEXT_21</Key>
    <Content>Παίζω</Content>
  </string>
  <string>
    <Key>TEXT_22</Key>
    <Content>Να σταματήσει</Content>
  </string>
  <string>
    <Key>TEXT_23</Key>
    <Content>  Συχνότητα</Content>
  </string>
  <string>
    <Key>TEXT_24</Key>
    <Content>  Τόμος</Content>
  </string>
  <string>
    <Key>TEXT_25</Key>
    <Content>  Πίσσα</Content>
  </string>
  <string>
    <Key>TEXT_26</Key>
    <Content>  Τηγάνι</Content>
  </string>
  <string>
    <Key>TEXT_27</Key>
    <Content>* Ομάδες καναλιών</Content>
  </string>
  <string>
    <Key>TEXT_28</Key>
    <Content>  DSP</Content>
  </string>
  <string>
    <Key>TEXT_29</Key>
    <Content>Ελεγξε τα ολα</Content>
  </string>
  <string>
    <Key>TEXT_30</Key>
    <Content>Ξετσεκαρε τα ολα</Content>
  </string>
  <string>
    <Key>TEXT_31</Key>
    <Content>Ορίστε την προεπιλεγμένη τιμή</Content>
  </string>
  <string>
    <Key>TEXT_32</Key>
    <Content>Επεξεργαστής χαρτών Pumpkins</Content>
  </string>
  <string>
    <Key>TEXT_33</Key>
    <Content>Αντικείμενο</Content>
  </string>
  <string>
    <Key>TEXT_34</Key>
    <Content>Φως</Content>
  </string>
  <string>
    <Key>TEXT_35</Key>
    <Content>Λίστα ματιών</Content>
  </string>
  <string>
    <Key>TEXT_36</Key>
    <Content>* Ρύθμιση λεπτομερειών σκηνής</Content>
  </string>
  <string>
    <Key>TEXT_37</Key>
    <Content>Διαδρομή δεδομένων:</Content>
  </string>
  <string>
    <Key>TEXT_38</Key>
    <Content>Αρχείο λίστας αντικειμένων:</Content>
  </string>
  <string>
    <Key>TEXT_39</Key>
    <Content>Αποθήκευση λίστας αντικειμένων</Content>
  </string>
  <string>
    <Key>TEXT_40</Key>
    <Content>Φόρτωση λίστας αντικειμένων</Content>
  </string>
  <string>
    <Key>TEXT_41</Key>
    <Content>* Ρύθμιση λεπτομέρειας στόχου αντικειμένου</Content>
  </string>
  <string>
    <Key>TEXT_42</Key>
    <Content>Δεν υπάρχει στόχος αντικειμένου.</Content>
  </string>
  <string>
    <Key>TEXT_43</Key>
    <Content>Κλειδαριά</Content>
  </string>
  <string>
    <Key>TEXT_44</Key>
    <Content>προβολή</Content>
  </string>
  <string>
    <Key>TEXT_45</Key>
    <Content>Κουτί</Content>
  </string>
  <string>
    <Key>TEXT_46</Key>
    <Content>Σύρμα</Content>
  </string>
  <string>
    <Key>TEXT_47</Key>
    <Content>Αναγνωριστικό πλέγματος:</Content>
  </string>
  <string>
    <Key>TEXT_48</Key>
    <Content>Θέση</Content>
  </string>
  <string>
    <Key>TEXT_49</Key>
    <Content>Περιστροφή</Content>
  </string>
  <string>
    <Key>TEXT_50</Key>
    <Content>Κλίμακα</Content>
  </string>
  <string>
    <Key>TEXT_51</Key>
    <Content>* Λίστες αντικειμένων</Content>
  </string>
  <string>
    <Key>TEXT_52</Key>
    <Content>* Ρύθμιση λεπτομέρειας φωτός</Content>
  </string>
  <string>
    <Key>TEXT_53</Key>
    <Content>Διαδρομή δεδομένων:</Content>
  </string>
  <string>
    <Key>TEXT_54</Key>
    <Content>Αρχείο Light:</Content>
  </string>
  <string>
    <Key>TEXT_55</Key>
    <Content>Light List Save</Content>
  </string>
  <string>
    <Key>TEXT_56</Key>
    <Content>Φόρτωση ελαφριάς λίστας</Content>
  </string>
  <string>
    <Key>TEXT_57</Key>
    <Content>Προσθήκη Ligts</Content>
  </string>
  <string>
    <Key>TEXT_58</Key>
    <Content>Κατευθυντήριος</Content>
  </string>
  <string>
    <Key>TEXT_59</Key>
    <Content>Σημείο</Content>
  </string>
  <string>
    <Key>TEXT_60</Key>
    <Content>Σημείο</Content>
  </string>
  <string>
    <Key>TEXT_61</Key>
    <Content>Αντιγραφή τρέχοντος φωτός</Content>
  </string>
  <string>
    <Key>TEXT_62</Key>
    <Content>* Ρύθμιση λεπτομέρειας στόχου φωτός</Content>
  </string>
  <string>
    <Key>TEXT_63</Key>
    <Content>Δεν υπάρχει ελαφρύς στόχος.</Content>
  </string>
  <string>
    <Key>TEXT_64</Key>
    <Content>Ονομα</Content>
  </string>
  <string>
    <Key>TEXT_65</Key>
    <Content>Κατεύθυνση</Content>
  </string>
  <string>
    <Key>TEXT_66</Key>
    <Content>Διαχέω</Content>
  </string>
  <string>
    <Key>TEXT_67</Key>
    <Content>Κατοπτρικός</Content>
  </string>
  <string>
    <Key>TEXT_68</Key>
    <Content>Περιβάλλων</Content>
  </string>
  <string>
    <Key>TEXT_69</Key>
    <Content>Στις δέκα</Content>
  </string>
  <string>
    <Key>TEXT_70</Key>
    <Content>Παράμετρος 1</Content>
  </string>
  <string>
    <Key>TEXT_71</Key>
    <Content>Παράμετρος 2</Content>
  </string>
  <string>
    <Key>TEXT_72</Key>
    <Content>* Light Lists</Content>
  </string>
  <string>
    <Key>TEXT_73</Key>
    <Content>Διαγράφω</Content>
  </string>
  <string>
    <Key>TEXT_74</Key>
    <Content>Προσθήκη αντικειμένου</Content>
  </string>
  <string>
    <Key>TEXT_75</Key>
    <Content>Μέγεθος</Content>
  </string>
  <string>
    <Key>TEXT_76</Key>
    <Content>* Τρέχων Ήχος Versoin:</Content>
  </string>
  <string>
    <Key>TEXT_77</Key>
    <Content>Συμπιεσμένο</Content>
  </string>
  <string>
    <Key>TEXT_78</Key>
    <Content>Ασυμπίεστος</Content>
  </string>
  <string>
    <Key>TEXT_79</Key>
    <Content>Ετικέτα ήχου</Content>
  </string>
</Language_Data>